redis_sentinel/RedisSentinel.py
redis_sentinel/__init__.py
redis_sentinel-1.0.1.dist-info/LICENSE
redis_sentinel-1.0.1.dist-info/METADATA
redis_sentinel-1.0.1.dist-info/WHEEL
redis_sentinel-1.0.1.dist-info/top_level.txt
redis_sentinel-1.0.1.dist-info/RECORD
