Metadata-Version: 2.1
Name: redis-sentinel
Version: 1.0.1
Summary: Redis connection fully managed by sentinel
Home-page: https://gitlab.com/kael_k/python-redis-sentinel
Author: kael_k (Kael D'Alcamo)
Author-email: dalcamkael@gmail.com
License: UNKNOWN
Platform: UNKNOWN
Requires-Python: >=3
Requires-Dist: redis (==3.*)
